Metadata-Version: 2.1
Name: InvoiceExtractor
Version: 0.1.2
Summary: A Python package for extracting data from invoices.
Home-page: https://github.com/ybrs/invoice-extractor
Author: Aybars Badur
